vsharecloudapi/__init__.py
vsharecloudapi/vsharecloudclient.py
vsharecloud_api-0.0.3.dist-info/LICENSE
vsharecloud_api-0.0.3.dist-info/METADATA
vsharecloud_api-0.0.3.dist-info/WHEEL
vsharecloud_api-0.0.3.dist-info/top_level.txt
vsharecloud_api-0.0.3.dist-info/RECORD
